parsetypes/__init__.py
parsetypes/_common.py
parsetypes/_compat.py
parsetypes/_parser.py
parsetypes/_reduce_types.py
parsetypes-0.3.3.dist-info/METADATA
parsetypes-0.3.3.dist-info/WHEEL
parsetypes-0.3.3.dist-info/top_level.txt
parsetypes-0.3.3.dist-info/RECORD
