Metadata-Version: 2.2
Name: parsetypes
Version: 0.3.3
Summary: Parse serialised data to recover their original underlying types
Author-email: Yu Shiyang <yu.shiyang@gnayihs.uy>
License: MPL-2.0
Project-URL: Homepage, https://github.com/yushiyangk/parsetypes
Project-URL: Documentation, https://parsetypes.gnayihs.uy/
Project-URL: Issues, https://github.com/yushiyangk/parsetypes/issues
Keywords: python,str,string,types,conversion
Classifier: Development Status :: 3 - Alpha
Classifier: Intended Audience :: Developers
Classifier: Intended Audience :: Information Technology
Classifier: Intended Audience :: Science/Research
Classifier: Intended Audience :: System Administrators
Classifier: License :: OSI Approved :: Mozilla Public License 2.0 (MPL 2.0)
Classifier: Operating System :: OS Independent
Classifier: Programming Language :: Python :: 3 :: Only
Classifier: Programming Language :: Python :: 3.9
Classifier: Programming Language :: Python :: 3.10
Classifier: Programming Language :: Python :: 3.11
Classifier: Programming Language :: Python :: 3.12
Classifier: Programming Language :: Python :: 3.13
Classifier: Topic :: File Formats
Classifier: Topic :: Office/Business
Classifier: Topic :: Scientific/Engineering :: Information Analysis
Classifier: Topic :: Scientific/Engineering :: Interface Engine/Protocol Translator
Classifier: Topic :: Software Development :: Libraries :: Python Modules
Classifier: Topic :: Utilities
Classifier: Typing :: Typed
Requires-Python: >=3.9
Provides-Extra: dev
Requires-Dist: pytest~=7.3.1; extra == "dev"
Requires-Dist: coverage~=7.2; extra == "dev"
Requires-Dist: pdoc~=13.1.1; extra == "dev"
Requires-Dist: pyroma~=4.2; extra == "dev"
Requires-Dist: build~=1.2.2; extra == "dev"
Requires-Dist: tox~=4.5.1; extra == "dev"
Requires-Dist: tox-extras==0.0.2; extra == "dev"
Provides-Extra: test
Requires-Dist: pytest~=7.3.1; extra == "test"
Requires-Dist: coverage~=7.2; extra == "test"
Provides-Extra: docs
Requires-Dist: pdoc~=13.1.1; extra == "docs"
Provides-Extra: metadata
Requires-Dist: pyroma~=4.2; extra == "metadata"
Provides-Extra: package
Requires-Dist: build~=1.2.2; extra == "package"
Provides-Extra: packagetest
Requires-Dist: twine~=6.0.1; extra == "packagetest"
Provides-Extra: ci
Requires-Dist: tox~=4.5.1; extra == "ci"
Requires-Dist: tox-extras==0.0.2; extra == "ci"
Provides-Extra: publish
Requires-Dist: twine~=6.0.1; extra == "publish"
